[
    {
      "img": "https://www.alagucrackers.in/Best-Crackers-Online-Theni/1753499340.jpg",
      "title": "VANITHA SPL SPINNER",
      "price": 189.0
    },
    {
      "img": "https://www.alagucrackers.in/Best-Crackers-Online-Theni/1753509985.jpg",
      "title": "SPINNER MIX",
      "price": 135.0
    },
    {
      "img": "https://www.alagucrackers.in/Best-Crackers-Online-Theni/1753510312.jpg",
      "title": "LOTTO",
      "price": 199.0
    },
    {
      "img": "https://www.alagucrackers.in/Best-Crackers-Online-Theni/1751895052.jpg",
      "title": "900 CC",
      "price": 159.0
    },
    {
      "img": "https://www.alagucrackers.in/Best-Crackers-Online-Theni/1751894746.jpg",
      "title": "4X4 WHEEL",
      "price": 159.0
    },
    {
      "img": "https://www.alagucrackers.in/Best-Crackers-Online-Theni/1753437485.jpg",
      "title": "WHISTLING DIXIE",
      "price": 94.0
    },
    {
      "img": "https://www.alagucrackers.in/Best-Crackers-Online-Theni/1753501735.jpg",
      "title": "RE-CYCLE",
      "price": 164.0
    },
    {
      "img": "https://www.alagucrackers.in/Best-Crackers-Online-Theni/1753437525.jpg",
      "title": "DISCO WHEEL 59",
      "price": 59.0
    },
    {
      "img": "https://www.alagucrackers.in/Best-Crackers-Online-Theni/1753437445.jpg",
      "title": "RING RING",
      "price": 133.0
    },
    {
      "img": "https://www.alagucrackers.in/Best-Crackers-Online-Theni/1753438531.jpg",
      "title": "JOY WHEEL",
      "price": 144.0
    },
    {
      "img": "https://www.alagucrackers.in/Best-Crackers-Online-Theni/1754820641.jpg",
      "title": "GC BIG (25 PCS)",
      "price": 47.0
    },
    {
      "img": "https://www.alagucrackers.in/Best-Crackers-Online-Theni/1753593413.jpg",
      "title": "GC SPECIAL",
      "price": 55.0
    },
    {
      "img": "https://www.alagucrackers.in/Best-Crackers-Online-Theni/175359251.jpg",
      "title": "DC DELUX",
      "price": 95.0
    },
    {
      "img": "https://www.alagucrackers.in/Best-Crackers-Online-Theni/1753592510.jpg",
      "title": "GC DELUX",
      "price": 99.0
    },
    {
      "img": "https://www.alagucrackers.in/Best-Crackers-Online-Theni/1753593538.jpg",
      "title": "GC SPINNER DELUX",
      "price": 155.0
    },
    {
      "img": "https://www.alagucrackers.in/Best-Crackers-Online-Theni/1754820317.jpg",
      "title": "GC SPINNER SPECIAL",
      "price": 139.0
    }
  ]
  