[
    
    {
        "image":"https://www.alagucrackers.in/Best-Crackers-Online-Theni/1723343327.jpg",
        "title":"Transperent gun",
        "price":65.00
    },
    {
        "image":"https://www.alagucrackers.in/Best-Crackers-Online-Theni/1723343419.jpg",
        "title":"Star silencer",
        "price":65.00
    },
    {
        "image":"https://www.alagucrackers.in/Best-Crackers-Online-Theni/1723343492.jpg",
        "title":"Fire 3",
        "price":45.00
    },
    {
        "image":"https://www.alagucrackers.in/Best-Crackers-Online-Theni/1723343543.jpg",
        "title":"Alpha black",
        "price":50.00
    },
    {
        "image":"https://www.alagucrackers.in/Best-Crackers-Online-Theni/1723343581.jpg",
        "title":"Ak 47",
        "price":290.00
    }
]